win_devices.pyd
win_devices-0.0.2.dist-info/DESCRIPTION.rst
win_devices-0.0.2.dist-info/METADATA
win_devices-0.0.2.dist-info/RECORD
win_devices-0.0.2.dist-info/WHEEL
win_devices-0.0.2.dist-info/metadata.json
win_devices-0.0.2.dist-info/top_level.txt
