Metadata-Version: 2.0
Name: win-devices
Version: 0.0.2
Summary: A module to return video devices connected to a Windows computer
Home-page: UNKNOWN
Author: Raphael Lumbroso
Author-email: raphael.lumbroso@angus.ai
License: UNKNOWN
Platform: UNKNOWN
